alibabacloud_cloudauth20190307/__init__.py
alibabacloud_cloudauth20190307/client.py
alibabacloud_cloudauth20190307/models/__init__.py
alibabacloud_cloudauth20190307/models/_aigcface_verify_request.py
alibabacloud_cloudauth20190307/models/_aigcface_verify_response.py
alibabacloud_cloudauth20190307/models/_aigcface_verify_response_body.py
alibabacloud_cloudauth20190307/models/_bank_meta_verify_request.py
alibabacloud_cloudauth20190307/models/_bank_meta_verify_response.py
alibabacloud_cloudauth20190307/models/_bank_meta_verify_response_body.py
alibabacloud_cloudauth20190307/models/_compare_face_verify_request.py
alibabacloud_cloudauth20190307/models/_compare_face_verify_response.py
alibabacloud_cloudauth20190307/models/_compare_face_verify_response_body.py
alibabacloud_cloudauth20190307/models/_compare_faces_request.py
alibabacloud_cloudauth20190307/models/_compare_faces_response.py
alibabacloud_cloudauth20190307/models/_compare_faces_response_body.py
alibabacloud_cloudauth20190307/models/_contrast_face_verify_advance_request.py
alibabacloud_cloudauth20190307/models/_contrast_face_verify_request.py
alibabacloud_cloudauth20190307/models/_contrast_face_verify_response.py
alibabacloud_cloudauth20190307/models/_contrast_face_verify_response_body.py
alibabacloud_cloudauth20190307/models/_create_ant_cloud_auth_scene_request.py
alibabacloud_cloudauth20190307/models/_create_ant_cloud_auth_scene_response.py
alibabacloud_cloudauth20190307/models/_create_ant_cloud_auth_scene_response_body.py
alibabacloud_cloudauth20190307/models/_create_auth_key_request.py
alibabacloud_cloudauth20190307/models/_create_auth_key_response.py
alibabacloud_cloudauth20190307/models/_create_auth_key_response_body.py
alibabacloud_cloudauth20190307/models/_create_cloudauthst_scene_request.py
alibabacloud_cloudauth20190307/models/_create_cloudauthst_scene_response.py
alibabacloud_cloudauth20190307/models/_create_cloudauthst_scene_response_body.py
alibabacloud_cloudauth20190307-3.13.1.dist-info/LICENSE
alibabacloud_cloudauth20190307-3.13.1.dist-info/METADATA
alibabacloud_cloudauth20190307-3.13.1.dist-info/WHEEL
alibabacloud_cloudauth20190307-3.13.1.dist-info/top_level.txt
alibabacloud_cloudauth20190307-3.13.1.dist-info/RECORD
